{
  "HALProvider": {
    "Other Devices": {
      "CANCoder (v6)[30]": {
        "header": {
          "open": true
        }
      },
      "CANCoder (v6)[31]": {
        "header": {
          "open": true
        }
      },
      "CANCoder (v6)[33]": {
        "header": {
          "open": true
        }
      },
      "SPARK MAX [10]": {
        "header": {
          "open": true
        }
      },
      "SPARK MAX [20]": {
        "header": {
          "open": true
        }
      },
      "SPARK MAX [21]": {
        "header": {
          "open": true
        }
      },
      "navX-Sensor[0]": {
        "header": {
          "open": true
        }
      }
    }
  },
  "NTProvider": {
    "types": {
      "/FMSInfo": "FMSInfo",
      "/SmartDashboard/Drive": "Subsystem",
      "/SmartDashboard/Elevator": "Subsystem",
      "/SmartDashboard/Field": "Field2d",
      "/SmartDashboard/Pickup": "Subsystem",
      "/SmartDashboard/Shooter": "Subsystem",
      "/SmartDashboard/Shooter Tilt": "Subsystem"
    },
    "windows": {
      "/SmartDashboard/Drive": {
        "window": {
          "visible": true
        }
      },
      "/SmartDashboard/Field": {
        "height": 8.013679504394531,
        "width": 16.541748046875,
        "window": {
          "visible": true
        }
      }
    }
  },
  "NetworkTables": {
    "transitory": {
      "SmartDashboard": {
        "Drive": {
          "open": true
        },
        "Elevator": {
          "open": true
        },
        "Field": {
          "double[]##v_/SmartDashboard/Field/Robot": {
            "open": true
          }
        },
        "Shooter Tilt": {
          "open": true
        },
        "open": true
      }
    }
  },
  "NetworkTables Info": {
    "visible": true
  }
}
